{
  "$schema": "http://json-schema.org/draft-07/schema#",
  "$id": "https://github.com/cubegb/cubegb/blob/main/cgb/schema.json",
  "title": "CubeGB .cgb format",
  "description": "Parametric primitive blockout format (source of truth). Version 0.1.",
  "type": "object",
  "required": ["format", "version", "units", "primitives"],
  "additionalProperties": false,
  "properties": {
    "format": {
      "const": "cgb"
    },
    "version": {
      "type": "string",
      "pattern": "^[0-9]+\\.[0-9]+$"
    },
    "metadata": {
      "type": "object",
      "additionalProperties": true,
      "properties": {
        "generator": { "type": "string" },
        "source_image": { "type": ["string", "null"] },
        "created_at": { "type": ["string", "null"] },
        "up_axis": { "type": "string", "enum": ["X", "Y", "Z"] }
      }
    },
    "units": {
      "type": "string",
      "enum": ["meter", "centimeter", "millimeter", "inch", "foot"]
    },
    "primitives": {
      "type": "array",
      "items": { "$ref": "#/definitions/primitive" }
    },
    "operations": {
      "type": "array",
      "description": "Declarative CSG. Each op references primitive ids; the baker computes the real mesh boolean once. operands[0] is the result/target, operands[1..] are the other operands (cutters for difference).",
      "items": { "$ref": "#/definitions/operation" }
    }
  },
  "definitions": {
    "vec3": {
      "type": "array",
      "items": { "type": "number" },
      "minItems": 3,
      "maxItems": 3
    },
    "color": {
      "type": "array",
      "items": { "type": "number", "minimum": 0, "maximum": 1 },
      "minItems": 3,
      "maxItems": 3
    },
    "transform": {
      "type": "object",
      "required": ["position", "rotation_euler", "scale"],
      "additionalProperties": false,
      "properties": {
        "position": { "$ref": "#/definitions/vec3" },
        "rotation_euler": {
          "$ref": "#/definitions/vec3",
          "description": "Radians, XYZ order."
        },
        "scale": { "$ref": "#/definitions/vec3" }
      }
    },
    "material": {
      "type": "object",
      "additionalProperties": false,
      "properties": {
        "color": { "$ref": "#/definitions/color" },
        "name": { "type": "string" }
      }
    },
    "deform": {
      "type": "object",
      "description": "Optional per-primitive shape deformations, applied in local space before the transform.",
      "additionalProperties": false,
      "properties": {
        "taper": {
          "type": "array",
          "description": "Cross-section scale at the +Y end relative to the -Y end (which stays 1). [x_ratio, z_ratio], linear along Y. Must be > 0.",
          "items": { "type": "number", "exclusiveMinimum": 0 },
          "minItems": 2,
          "maxItems": 2
        },
        "bevel": {
          "type": "number",
          "description": "Chamfer/round the edges (cube only in v1). Ratio 0..0.5 of the shortest edge; 0 = sharp, 0.5 = fully rounded shortest edge.",
          "minimum": 0,
          "maximum": 0.5
        },
        "shear": {
          "type": "array",
          "description": "Tilt along +Y: the +Y end is offset by [x_slope, z_slope] * height relative to the -Y end (which stays put), linear along Y. A slope of 1 leans 45 degrees.",
          "items": { "type": "number" },
          "minItems": 2,
          "maxItems": 2
        }
      }
    },
    "primitive": {
      "type": "object",
      "required": ["id", "type", "transform", "params"],
      "additionalProperties": false,
      "properties": {
        "id": { "type": "string", "minLength": 1 },
        "name": { "type": "string" },
        "type": {
          "type": "string",
          "enum": ["cube", "sphere", "cylinder", "cone"]
        },
        "transform": { "$ref": "#/definitions/transform" },
        "params": { "type": "object" },
        "deform": { "$ref": "#/definitions/deform" },
        "material": { "$ref": "#/definitions/material" },
        "parent": { "type": ["string", "null"] }
      },
      "allOf": [
        {
          "if": { "properties": { "type": { "const": "cube" } } },
          "then": {
            "properties": {
              "params": {
                "type": "object",
                "required": ["size"],
                "additionalProperties": false,
                "properties": {
                  "size": { "$ref": "#/definitions/vec3" }
                }
              }
            }
          }
        },
        {
          "if": { "properties": { "type": { "const": "sphere" } } },
          "then": {
            "properties": {
              "params": {
                "type": "object",
                "required": ["radius"],
                "additionalProperties": false,
                "properties": {
                  "radius": { "type": "number", "exclusiveMinimum": 0 },
                  "segments": { "type": "integer", "minimum": 3 }
                }
              }
            }
          }
        },
        {
          "if": { "properties": { "type": { "const": "cylinder" } } },
          "then": {
            "properties": {
              "params": {
                "type": "object",
                "required": ["radius", "height"],
                "additionalProperties": false,
                "properties": {
                  "radius": { "type": "number", "exclusiveMinimum": 0 },
                  "height": { "type": "number", "exclusiveMinimum": 0 },
                  "segments": { "type": "integer", "minimum": 3 },
                  "sweep_start": { "type": "number", "minimum": 0, "maximum": 360 },
                  "sweep_end": { "type": "number", "minimum": 0, "maximum": 360 },
                  "sweep_caps": { "type": "boolean" }
                }
              }
            }
          }
        },
        {
          "if": { "properties": { "type": { "const": "cone" } } },
          "then": {
            "properties": {
              "params": {
                "type": "object",
                "required": ["radius", "height"],
                "additionalProperties": false,
                "properties": {
                  "radius": { "type": "number", "exclusiveMinimum": 0 },
                  "height": { "type": "number", "exclusiveMinimum": 0 },
                  "segments": { "type": "integer", "minimum": 3 },
                  "sweep_start": { "type": "number", "minimum": 0, "maximum": 360 },
                  "sweep_end": { "type": "number", "minimum": 0, "maximum": 360 },
                  "sweep_caps": { "type": "boolean" }
                }
              }
            }
          }
        }
      ]
    },
    "operation": {
      "type": "object",
      "required": ["type", "operands"],
      "additionalProperties": true,
      "properties": {
        "type": {
          "type": "string",
          "enum": ["union", "difference", "intersection"]
        },
        "operands": {
          "type": "array",
          "description": "Primitive ids. operands[0] is the result/target; operands[1..] are the other operands (cutters for difference).",
          "items": { "type": "string" },
          "minItems": 2
        },
        "name": { "type": "string" }
      }
    }
  }
}
